labelkit/__init__.py
labelkit/grid_search.py
labelkit/llm.py
labelkit/models.py
labelkit/openai.py
labelkit/pipeline.py
labelkit/pydantic.py
labelkit/steps/__init__.py
labelkit/steps/custom.py
labelkit/steps/embedding_classification.py
labelkit/steps/llm_step.py
labelkit/steps/serp.py
labelkit/steps/step.py
labelkit/util.py
labelkit-0.1.0.dist-info/METADATA
labelkit-0.1.0.dist-info/WHEEL
labelkit-0.1.0.dist-info/RECORD
