Metadata-Version: 2.1
Name: labelkit
Version: 0.1.0
Summary: build unstructured to structured data transformation pipelines
Home-page: https://github.com/villagecomputing/labelkit
License: MIT
Author: Aman Dhesi
Author-email: aman@stelolabs.com
Requires-Python: >=3.10,<4.0
Classifier: License :: OSI Approved :: MIT License
Classifier: Programming Language :: Python :: 3
Classifier: Programming Language :: Python :: 3.10
Classifier: Programming Language :: Python :: 3.11
Requires-Dist: cohere (>=4.38,<5.0)
Requires-Dist: faiss-cpu (>=1.7.4,<2.0.0)
Requires-Dist: numpy (>=1.26.2,<2.0.0)
Requires-Dist: openai (>=1.3.9,<2.0.0)
Requires-Dist: pandas (>=2.1.4,<3.0.0)
Requires-Dist: pydantic (>=2.6.1,<3.0.0)
Project-URL: Repository, https://github.com/villagecomputing/labelkit
